kts_cli/__init__.py
kts_cli/examples.py
kts_cli/file_system.py
kts_cli-0.0.18.dist-info/LICENSE
kts_cli-0.0.18.dist-info/METADATA
kts_cli-0.0.18.dist-info/WHEEL
kts_cli-0.0.18.dist-info/entry_points.txt
kts_cli-0.0.18.dist-info/top_level.txt
kts_cli-0.0.18.dist-info/RECORD
