Metadata-Version: 2.1
Name: kts-cli
Version: 0.0.18
Summary: Command line interface for kts package
Home-page: https://github.com/konodyuk/kts-cli
Author: Nikita Konodyuk
Author-email: konodyuk@gmail.com
License: UNKNOWN
Platform: UNKNOWN
Classifier: Programming Language :: Python :: 3
Classifier: License :: OSI Approved :: MIT License
Classifier: Operating System :: OS Independent
